{
  "RECORDS": [
    {
      "Id": 6,
      "ParentId": 0,
      "Title": "物联网关",
      "Code": "System",
      "Category": "MODULE",
      "Target": "_self",
      "Href": "",
      "Icon": "fa-solid fa-house-user",

      "CreateTime": null,
      "CreateUser": null,
      "CreateUserId": 0,
      "IsDelete": "0",
      "UpdateTime": null,
      "UpdateUser": null,
      "UpdateUserId": null,
      "SortCode": 0,
      "ExtJson": null
    },

    {
      "Id": 61100022003,
      "ParentId": 6100001,
      "Module": 6,
      "Title": "系统配置",
      "Icon": "fas fa-journal-whills",
      "Code": "System",
      "Category": 1,
      "Target": 0,
      "NavLinkMatch": 1,
      "Href": "/gateway/system",
      "CreateTime": "5/11/2024 04:08:09.88",
      "CreateUser": null,
      "CreateUserId": 0,
      "IsDelete": "0",
      "UpdateTime": "5/11/2024 04:28:42.79",
      "UpdateUser": null,
      "UpdateUserId": null,
      "SortCode": -1,
      "ExtJson": null
    },
    {
      "Id": 61000022002001,
      "ParentId": 61000022002,
      "Module": 6,
      "Title": "写入变量",
      "Icon": null,
      "Code": "System",
      "Category": 2,
      "Target": null,
      "NavLinkMatch": null,
      "Href": null,
      "CreateTime": "5/11/2024 04:08:09.92",
      "CreateUser": "SuperAdmin",
      "CreateUserId": 212725263002001,
      "IsDelete": "0",
      "UpdateTime": "5/11/2024 04:28:42.83",
      "UpdateUser": null,
      "UpdateUserId": null,
      "SortCode": null,
      "ExtJson": null
    },
    {
      "Id": 61000022001006,
      "ParentId": 61000022001,
      "Module": 6,
      "Title": "删除缓存",
      "Icon": null,
      "Code": "System",
      "Category": 2,
      "Target": null,
      "NavLinkMatch": null,
      "Href": null,
      "CreateTime": "5/11/2024 04:08:09.92",
      "CreateUser": "SuperAdmin",
      "CreateUserId": 212725263002001,
      "IsDelete": "0",
      "UpdateTime": "5/11/2024 04:28:42.83",
      "UpdateUser": null,
      "UpdateUserId": null,
      "SortCode": null,
      "ExtJson": null
    },
    {
      "Id": 61000022001005,
      "ParentId": 61000022001,
      "Module": 6,
      "Title": "切换冗余",
      "Icon": null,
      "Code": "System",
      "Category": 2,
      "Target": null,
      "NavLinkMatch": null,
      "Href": null,
      "CreateTime": "5/11/2024 04:08:09.92",
      "CreateUser": "SuperAdmin",
      "CreateUserId": 212725263002001,
      "IsDelete": "0",
      "UpdateTime": "5/11/2024 04:28:42.83",
      "UpdateUser": null,
      "UpdateUserId": null,
      "SortCode": null,
      "ExtJson": null
    },
    {
      "Id": 61000022001004,
      "ParentId": 61000022001,
      "Module": 6,
      "Title": "暂停",
      "Icon": null,
      "Code": "System",
      "Category": 2,
      "Target": null,
      "NavLinkMatch": null,
      "Href": null,
      "CreateTime": "5/11/2024 04:08:09.92",
      "CreateUser": "SuperAdmin",
      "CreateUserId": 212725263002001,
      "IsDelete": "0",
      "UpdateTime": "5/11/2024 04:28:42.83",
      "UpdateUser": null,
      "UpdateUserId": null,
      "SortCode": null,
      "ExtJson": null
    },
    {
      "Id": 61000022001003,
      "ParentId": 61000022001,
      "Module": 6,
      "Title": "通道日志",
      "Icon": null,
      "Code": "System",
      "Category": 2,
      "Target": null,
      "NavLinkMatch": null,
      "Href": null,
      "CreateTime": "5/11/2024 04:08:09.92",
      "CreateUser": "SuperAdmin",
      "CreateUserId": 212725263002001,
      "IsDelete": "0",
      "UpdateTime": "5/11/2024 04:28:42.83",
      "UpdateUser": null,
      "UpdateUserId": null,
      "SortCode": null,
      "ExtJson": null
    },
    {
      "Id": 61000022001002,
      "ParentId": 61000022001,
      "Module": 6,
      "Title": "重启",
      "Icon": null,
      "Code": "System",
      "Category": 2,
      "Target": null,
      "NavLinkMatch": null,
      "Href": null,
      "CreateTime": "5/11/2024 04:08:09.92",
      "CreateUser": "SuperAdmin",
      "CreateUserId": 212725263002001,
      "IsDelete": "0",
      "UpdateTime": "5/11/2024 04:28:42.83",
      "UpdateUser": null,
      "UpdateUserId": null,
      "SortCode": null,
      "ExtJson": null
    },
    {
      "Id": 61000022001001,
      "ParentId": 61000022001,
      "Module": 6,
      "Title": "插件页面",
      "Icon": null,
      "Code": "System",
      "Category": 2,
      "Target": null,
      "NavLinkMatch": null,
      "Href": null,
      "CreateTime": "5/11/2024 04:08:09.92",
      "CreateUser": "SuperAdmin",
      "CreateUserId": 212725263002001,
      "IsDelete": "0",
      "UpdateTime": "5/11/2024 04:28:42.83",
      "UpdateUser": null,
      "UpdateUserId": null,
      "SortCode": null,
      "ExtJson": null
    },
    {
      "Id": 61000012005007,
      "ParentId": 61000012005,
      "Module": 6,
      "Title": "测试",
      "Icon": null,
      "Code": "System",
      "Category": 2,
      "Target": null,
      "NavLinkMatch": null,
      "Href": null,
      "CreateTime": "5/11/2024 04:08:09.92",
      "CreateUser": "SuperAdmin",
      "CreateUserId": 212725263002001,
      "IsDelete": "0",
      "UpdateTime": "5/11/2024 04:28:42.83",
      "UpdateUser": null,
      "UpdateUserId": null,
      "SortCode": null,
      "ExtJson": null
    },
    {
      "Id": 61000012005006,
      "ParentId": 61000012005,
      "Module": 6,
      "Title": "清空",
      "Icon": null,
      "Code": "System",
      "Category": 2,
      "Target": null,
      "NavLinkMatch": null,
      "Href": null,
      "CreateTime": "5/11/2024 04:08:09.92",
      "CreateUser": "SuperAdmin",
      "CreateUserId": 212725263002001,
      "IsDelete": "0",
      "UpdateTime": "5/11/2024 04:28:42.83",
      "UpdateUser": null,
      "UpdateUserId": null,
      "SortCode": null,
      "ExtJson": null
    },
    {
      "Id": 61000012005005,
      "ParentId": 61000012005,
      "Module": 6,
      "Title": "导入",
      "Icon": null,
      "Code": "System",
      "Category": 2,
      "Target": null,
      "NavLinkMatch": null,
      "Href": null,
      "CreateTime": "5/11/2024 04:08:09.92",
      "CreateUser": "SuperAdmin",
      "CreateUserId": 212725263002001,
      "IsDelete": "0",
      "UpdateTime": "5/11/2024 04:28:42.83",
      "UpdateUser": null,
      "UpdateUserId": null,
      "SortCode": null,
      "ExtJson": null
    },
    {
      "Id": 61000012005004,
      "ParentId": 61000012005,
      "Module": 6,
      "Title": "导出",
      "Icon": null,
      "Code": "System",
      "Category": 2,
      "Target": null,
      "NavLinkMatch": null,
      "Href": null,
      "CreateTime": "5/11/2024 04:08:09.92",
      "CreateUser": "SuperAdmin",
      "CreateUserId": 212725263002001,
      "IsDelete": "0",
      "UpdateTime": "5/11/2024 04:28:42.83",
      "UpdateUser": null,
      "UpdateUserId": null,
      "SortCode": null,
      "ExtJson": null
    },
    {
      "Id": 61000012005003,
      "ParentId": 61000012005,
      "Module": 6,
      "Title": "删除",
      "Icon": null,
      "Code": "System",
      "Category": 2,
      "Target": null,
      "NavLinkMatch": null,
      "Href": null,
      "CreateTime": "5/11/2024 04:08:09.92",
      "CreateUser": "SuperAdmin",
      "CreateUserId": 212725263002001,
      "IsDelete": "0",
      "UpdateTime": "5/11/2024 04:28:42.83",
      "UpdateUser": null,
      "UpdateUserId": null,
      "SortCode": null,
      "ExtJson": null
    },
    {
      "Id": 61000012005002,
      "ParentId": 61000012005,
      "Module": 6,
      "Title": "编辑",
      "Icon": null,
      "Code": "System",
      "Category": 2,
      "Target": null,
      "NavLinkMatch": null,
      "Href": null,
      "CreateTime": "5/11/2024 04:08:09.92",
      "CreateUser": "SuperAdmin",
      "CreateUserId": 212725263002001,
      "IsDelete": "0",
      "UpdateTime": "5/11/2024 04:28:42.83",
      "UpdateUser": null,
      "UpdateUserId": null,
      "SortCode": null,
      "ExtJson": null
    },
    {
      "Id": 61000012005001,
      "ParentId": 61000012005,
      "Module": 6,
      "Title": "新增",
      "Icon": null,
      "Code": "System",
      "Category": 2,
      "Target": null,
      "NavLinkMatch": null,
      "Href": null,
      "CreateTime": "5/11/2024 04:08:09.92",
      "CreateUser": "SuperAdmin",
      "CreateUserId": 212725263002001,
      "IsDelete": "0",
      "UpdateTime": "5/11/2024 04:28:42.83",
      "UpdateUser": null,
      "UpdateUserId": null,
      "SortCode": null,
      "ExtJson": null
    },
    {
      "Id": 61000012004006,
      "ParentId": 61000012004,
      "Module": 6,
      "Title": "清空",
      "Icon": null,
      "Code": "System",
      "Category": 2,
      "Target": null,
      "NavLinkMatch": null,
      "Href": null,
      "CreateTime": "5/11/2024 04:08:09.92",
      "CreateUser": "SuperAdmin",
      "CreateUserId": 212725263002001,
      "IsDelete": "0",
      "UpdateTime": "5/11/2024 04:28:42.83",
      "UpdateUser": null,
      "UpdateUserId": null,
      "SortCode": null,
      "ExtJson": null
    },
    {
      "Id": 61000012004005,
      "ParentId": 61000012004,
      "Module": 6,
      "Title": "导入",
      "Icon": null,
      "Code": "System",
      "Category": 2,
      "Target": null,
      "NavLinkMatch": null,
      "Href": null,
      "CreateTime": "5/11/2024 04:08:09.92",
      "CreateUser": "SuperAdmin",
      "CreateUserId": 212725263002001,
      "IsDelete": "0",
      "UpdateTime": "5/11/2024 04:28:42.83",
      "UpdateUser": null,
      "UpdateUserId": null,
      "SortCode": null,
      "ExtJson": null
    },
    {
      "Id": 61000012004004,
      "ParentId": 61000012004,
      "Module": 6,
      "Title": "导出",
      "Icon": null,
      "Code": "System",
      "Category": 2,
      "Target": null,
      "NavLinkMatch": null,
      "Href": null,
      "CreateTime": "5/11/2024 04:08:09.92",
      "CreateUser": "SuperAdmin",
      "CreateUserId": 212725263002001,
      "IsDelete": "0",
      "UpdateTime": "5/11/2024 04:28:42.83",
      "UpdateUser": null,
      "UpdateUserId": null,
      "SortCode": null,
      "ExtJson": null
    },
    {
      "Id": 61000012004003,
      "ParentId": 61000012004,
      "Module": 6,
      "Title": "删除",
      "Icon": null,
      "Code": "System",
      "Category": 2,
      "Target": null,
      "NavLinkMatch": null,
      "Href": null,
      "CreateTime": "5/11/2024 04:08:09.92",
      "CreateUser": "SuperAdmin",
      "CreateUserId": 212725263002001,
      "IsDelete": "0",
      "UpdateTime": "5/11/2024 04:28:42.83",
      "UpdateUser": null,
      "UpdateUserId": null,
      "SortCode": null,
      "ExtJson": null
    },
    {
      "Id": 61000012004002,
      "ParentId": 61000012004,
      "Module": 6,
      "Title": "编辑",
      "Icon": null,
      "Code": "System",
      "Category": 2,
      "Target": null,
      "NavLinkMatch": null,
      "Href": null,
      "CreateTime": "5/11/2024 04:08:09.92",
      "CreateUser": "SuperAdmin",
      "CreateUserId": 212725263002001,
      "IsDelete": "0",
      "UpdateTime": "5/11/2024 04:28:42.83",
      "UpdateUser": null,
      "UpdateUserId": null,
      "SortCode": null,
      "ExtJson": null
    },
    {
      "Id": 61000012004001,
      "ParentId": 61000012004,
      "Module": 6,
      "Title": "新增",
      "Icon": null,
      "Code": "System",
      "Category": 2,
      "Target": null,
      "NavLinkMatch": null,
      "Href": null,
      "CreateTime": "5/11/2024 04:08:09.92",
      "CreateUser": "SuperAdmin",
      "CreateUserId": 212725263002001,
      "IsDelete": "0",
      "UpdateTime": "5/11/2024 04:28:42.83",
      "UpdateUser": null,
      "UpdateUserId": null,
      "SortCode": null,
      "ExtJson": null
    },
    {
      "Id": 61000012003006,
      "ParentId": 61000012003,
      "Module": 6,
      "Title": "清空",
      "Icon": null,
      "Code": "System",
      "Category": 2,
      "Target": null,
      "NavLinkMatch": null,
      "Href": null,
      "CreateTime": "5/11/2024 04:08:09.92",
      "CreateUser": "SuperAdmin",
      "CreateUserId": 212725263002001,
      "IsDelete": "0",
      "UpdateTime": "5/11/2024 04:28:42.83",
      "UpdateUser": null,
      "UpdateUserId": null,
      "SortCode": null,
      "ExtJson": null
    },
    {
      "Id": 61000012003005,
      "ParentId": 61000012003,
      "Module": 6,
      "Title": "导入",
      "Icon": null,
      "Code": "System",
      "Category": 2,
      "Target": null,
      "NavLinkMatch": null,
      "Href": null,
      "CreateTime": "5/11/2024 04:08:09.92",
      "CreateUser": "SuperAdmin",
      "CreateUserId": 212725263002001,
      "IsDelete": "0",
      "UpdateTime": "5/11/2024 04:28:42.83",
      "UpdateUser": null,
      "UpdateUserId": null,
      "SortCode": null,
      "ExtJson": null
    },
    {
      "Id": 61000012003004,
      "ParentId": 61000012003,
      "Module": 6,
      "Title": "导出",
      "Icon": null,
      "Code": "System",
      "Category": 2,
      "Target": null,
      "NavLinkMatch": null,
      "Href": null,
      "CreateTime": "5/11/2024 04:08:09.92",
      "CreateUser": "SuperAdmin",
      "CreateUserId": 212725263002001,
      "IsDelete": "0",
      "UpdateTime": "5/11/2024 04:28:42.827",
      "UpdateUser": null,
      "UpdateUserId": null,
      "SortCode": null,
      "ExtJson": null
    },
    {
      "Id": 61000012003003,
      "ParentId": 61000012003,
      "Module": 6,
      "Title": "删除",
      "Icon": null,
      "Code": "System",
      "Category": 2,
      "Target": null,
      "NavLinkMatch": null,
      "Href": null,
      "CreateTime": "5/11/2024 04:08:09.92",
      "CreateUser": "SuperAdmin",
      "CreateUserId": 212725263002001,
      "IsDelete": "0",
      "UpdateTime": "5/11/2024 04:28:42.827",
      "UpdateUser": null,
      "UpdateUserId": null,
      "SortCode": null,
      "ExtJson": null
    },
    {
      "Id": 61000012003002,
      "ParentId": 61000012003,
      "Module": 6,
      "Title": "编辑",
      "Icon": null,
      "Code": "System",
      "Category": 2,
      "Target": null,
      "NavLinkMatch": null,
      "Href": null,
      "CreateTime": "5/11/2024 04:08:09.92",
      "CreateUser": "SuperAdmin",
      "CreateUserId": 212725263002001,
      "IsDelete": "0",
      "UpdateTime": "5/11/2024 04:28:42.827",
      "UpdateUser": null,
      "UpdateUserId": null,
      "SortCode": null,
      "ExtJson": null
    },
    {
      "Id": 61000012003001,
      "ParentId": 61000012003,
      "Module": 6,
      "Title": "新增",
      "Icon": null,
      "Code": "System",
      "Category": 2,
      "Target": null,
      "NavLinkMatch": null,
      "Href": null,
      "CreateTime": "5/11/2024 04:08:09.92",
      "CreateUser": "SuperAdmin",
      "CreateUserId": 212725263002001,
      "IsDelete": "0",
      "UpdateTime": "5/11/2024 04:28:42.827",
      "UpdateUser": null,
      "UpdateUserId": null,
      "SortCode": null,
      "ExtJson": null
    },
    {
      "Id": 61000012002006,
      "ParentId": 61000012002,
      "Module": 6,
      "Title": "清空",
      "Icon": null,
      "Code": "System",
      "Category": 2,
      "Target": null,
      "NavLinkMatch": null,
      "Href": null,
      "CreateTime": "5/11/2024 04:08:09.92",
      "CreateUser": "SuperAdmin",
      "CreateUserId": 212725263002001,
      "IsDelete": "0",
      "UpdateTime": "5/11/2024 04:28:42.827",
      "UpdateUser": null,
      "UpdateUserId": null,
      "SortCode": null,
      "ExtJson": null
    },
    {
      "Id": 61000012002005,
      "ParentId": 61000012002,
      "Module": 6,
      "Title": "导入",
      "Icon": null,
      "Code": "System",
      "Category": 2,
      "Target": null,
      "NavLinkMatch": null,
      "Href": null,
      "CreateTime": "5/11/2024 04:08:09.92",
      "CreateUser": "SuperAdmin",
      "CreateUserId": 212725263002001,
      "IsDelete": "0",
      "UpdateTime": "5/11/2024 04:28:42.827",
      "UpdateUser": null,
      "UpdateUserId": null,
      "SortCode": null,
      "ExtJson": null
    },
    {
      "Id": 61000012002004,
      "ParentId": 61000012002,
      "Module": 6,
      "Title": "导出",
      "Icon": null,
      "Code": "System",
      "Category": 2,
      "Target": null,
      "NavLinkMatch": null,
      "Href": null,
      "CreateTime": "5/11/2024 04:08:09.92",
      "CreateUser": "SuperAdmin",
      "CreateUserId": 212725263002001,
      "IsDelete": "0",
      "UpdateTime": "5/11/2024 04:28:42.827",
      "UpdateUser": null,
      "UpdateUserId": null,
      "SortCode": null,
      "ExtJson": null
    },
    {
      "Id": 61000012002003,
      "ParentId": 61000012002,
      "Module": 6,
      "Title": "删除",
      "Icon": null,
      "Code": "System",
      "Category": 2,
      "Target": null,
      "NavLinkMatch": null,
      "Href": null,
      "CreateTime": "5/11/2024 04:08:09.92",
      "CreateUser": "SuperAdmin",
      "CreateUserId": 212725263002001,
      "IsDelete": "0",
      "UpdateTime": "5/11/2024 04:28:42.827",
      "UpdateUser": null,
      "UpdateUserId": null,
      "SortCode": null,
      "ExtJson": null
    },
    {
      "Id": 61000012002002,
      "ParentId": 61000012002,
      "Module": 6,
      "Title": "编辑",
      "Icon": null,
      "Code": "System",
      "Category": 2,
      "Target": null,
      "NavLinkMatch": null,
      "Href": null,
      "CreateTime": "5/11/2024 04:08:09.92",
      "CreateUser": "SuperAdmin",
      "CreateUserId": 212725263002001,
      "IsDelete": "0",
      "UpdateTime": "5/11/2024 04:28:42.827",
      "UpdateUser": null,
      "UpdateUserId": null,
      "SortCode": null,
      "ExtJson": null
    },
    {
      "Id": 61000012002001,
      "ParentId": 61000012002,
      "Module": 6,
      "Title": "新增",
      "Icon": null,
      "Code": "System",
      "Category": 2,
      "Target": null,
      "NavLinkMatch": null,
      "Href": null,
      "CreateTime": "5/11/2024 04:08:09.92",
      "CreateUser": "SuperAdmin",
      "CreateUserId": 212725263002001,
      "IsDelete": "0",
      "UpdateTime": "5/11/2024 04:28:42.827",
      "UpdateUser": null,
      "UpdateUserId": null,
      "SortCode": null,
      "ExtJson": null
    },
    {
      "Id": 61000012001002,
      "ParentId": 61000012001,
      "Module": 6,
      "Title": "导出",
      "Icon": null,
      "Code": "System",
      "Category": 2,
      "Target": null,
      "NavLinkMatch": null,
      "Href": null,
      "CreateTime": "5/11/2024 04:08:09.92",
      "CreateUser": "SuperAdmin",
      "CreateUserId": 212725263002001,
      "IsDelete": "0",
      "UpdateTime": "5/11/2024 04:28:42.827",
      "UpdateUser": null,
      "UpdateUserId": null,
      "SortCode": null,
      "ExtJson": null
    },
    {
      "Id": 61000012001001,
      "ParentId": 61000012001,
      "Module": 6,
      "Title": "新增",
      "Icon": null,
      "Code": "System",
      "Category": 2,
      "Target": null,
      "NavLinkMatch": null,
      "Href": null,
      "CreateTime": "5/11/2024 04:08:09.92",
      "CreateUser": "SuperAdmin",
      "CreateUserId": 212725263002001,
      "IsDelete": "0",
      "UpdateTime": "5/11/2024 04:28:42.827",
      "UpdateUser": null,
      "UpdateUserId": null,
      "SortCode": null,
      "ExtJson": null
    },
    {
      "Id": 61000032002,
      "ParentId": 6100003,
      "Module": 6,
      "Title": "RPC日志",
      "Icon": "fas fa-journal-whills",
      "Code": "System",
      "Category": 1,
      "Target": 0,
      "NavLinkMatch": 1,
      "Href": "/gateway/rpclog",
      "CreateTime": "5/11/2024 04:08:09.92",
      "CreateUser": null,
      "CreateUserId": 0,
      "IsDelete": "0",
      "UpdateTime": "5/11/2024 04:28:42.827",
      "UpdateUser": null,
      "UpdateUserId": null,
      "SortCode": 2,
      "ExtJson": null
    },
    {
      "Id": 61000032001,
      "ParentId": 6100003,
      "Module": 6,
      "Title": "后台日志",
      "Icon": "fas fa-journal-whills",
      "Code": "System",
      "Category": 1,
      "Target": 0,
      "NavLinkMatch": 1,
      "Href": "/gateway/backendlog",
      "CreateTime": "5/11/2024 04:08:09.92",
      "CreateUser": null,
      "CreateUserId": 0,
      "IsDelete": "0",
      "UpdateTime": "5/11/2024 04:28:42.827",
      "UpdateUser": null,
      "UpdateUserId": null,
      "SortCode": 1,
      "ExtJson": null
    },
    {
      "Id": 61000022003,
      "ParentId": 6100002,
      "Module": 6,
      "Title": "实时报警",
      "Icon": "fas fa-journal-whills",
      "Code": "System",
      "Category": 1,
      "Target": 0,
      "NavLinkMatch": 1,
      "Href": "/gateway/realalarm",
      "CreateTime": "5/11/2024 04:08:09.92",
      "CreateUser": null,
      "CreateUserId": 0,
      "IsDelete": "0",
      "UpdateTime": "5/11/2024 04:28:42.827",
      "UpdateUser": null,
      "UpdateUserId": null,
      "SortCode": 3,
      "ExtJson": null
    },
    {
      "Id": 61000022002,
      "ParentId": 6100002,
      "Module": 6,
      "Title": "实时数据",
      "Icon": "fas fa-journal-whills",
      "Code": "System",
      "Category": 1,
      "Target": 0,
      "NavLinkMatch": 0,
      "Href": "/gateway/variableruntime",
      "CreateTime": "5/11/2024 04:08:09.92",
      "CreateUser": null,
      "CreateUserId": 0,
      "IsDelete": "0",
      "UpdateTime": "5/11/2024 04:28:42.827",
      "UpdateUser": null,
      "UpdateUserId": null,
      "SortCode": 2,
      "ExtJson": null
    },
    {
      "Id": 61000022001,
      "ParentId": 6100002,
      "Module": 6,
      "Title": "设备状态",
      "Icon": "fas fa-journal-whills",
      "Code": "System",
      "Category": 1,
      "Target": 0,
      "NavLinkMatch": 1,
      "Href": "/gateway/devicestatus",
      "CreateTime": "5/11/2024 04:08:09.92",
      "CreateUser": null,
      "CreateUserId": 0,
      "IsDelete": "0",
      "UpdateTime": "5/11/2024 04:28:42.827",
      "UpdateUser": null,
      "UpdateUserId": null,
      "SortCode": 1,
      "ExtJson": null
    },
    {
      "Id": 61000012005,
      "ParentId": 6100001,
      "Module": 6,
      "Title": "变量管理",
      "Icon": "fas fa-bezier-curve",
      "Code": "System",
      "Category": 1,
      "Target": 0,
      "NavLinkMatch": 0,
      "Href": "/gateway/variable",
      "CreateTime": "5/11/2024 04:08:09.92",
      "CreateUser": null,
      "CreateUserId": 0,
      "IsDelete": "0",
      "UpdateTime": "5/11/2024 04:28:42.827",
      "UpdateUser": null,
      "UpdateUserId": null,
      "SortCode": 4,
      "ExtJson": null
    },
    {
      "Id": 61000012004,
      "ParentId": 6100001,
      "Module": 6,
      "Title": "业务设备",
      "Icon": "fas fa-bezier-curve",
      "Code": "System",
      "Category": 1,
      "Target": 0,
      "NavLinkMatch": 1,
      "Href": "/gateway/businessdevice",
      "CreateTime": "5/11/2024 04:08:09.92",
      "CreateUser": null,
      "CreateUserId": 0,
      "IsDelete": "0",
      "UpdateTime": "5/11/2024 04:28:42.827",
      "UpdateUser": null,
      "UpdateUserId": null,
      "SortCode": 3,
      "ExtJson": null
    },
    {
      "Id": 61000012003,
      "ParentId": 6100001,
      "Module": 6,
      "Title": "采集设备",
      "Icon": "fas fa-bezier-curve",
      "Code": "System",
      "Category": 1,
      "Target": 0,
      "NavLinkMatch": 1,
      "Href": "/gateway/collectdevice",
      "CreateTime": "5/11/2024 04:08:09.92",
      "CreateUser": null,
      "CreateUserId": 0,
      "IsDelete": "0",
      "UpdateTime": "5/11/2024 04:28:42.827",
      "UpdateUser": null,
      "UpdateUserId": null,
      "SortCode": 2,
      "ExtJson": null
    },
    {
      "Id": 61000012002,
      "ParentId": 6100001,
      "Module": 6,
      "Title": "通道管理",
      "Icon": "fas fa-bezier-curve",
      "Code": "System",
      "Category": 1,
      "Target": 0,
      "NavLinkMatch": 1,
      "Href": "/gateway/channel",
      "CreateTime": "5/11/2024 04:08:09.92",
      "CreateUser": null,
      "CreateUserId": 0,
      "IsDelete": "0",
      "UpdateTime": "5/11/2024 04:28:42.827",
      "UpdateUser": null,
      "UpdateUserId": null,
      "SortCode": 1,
      "ExtJson": null
    },
    {
      "Id": 61000012001,
      "ParentId": 6100001,
      "Module": 6,
      "Title": "插件管理",
      "Icon": "fas fa-bezier-curve",
      "Code": "System",
      "Category": 1,
      "Target": 0,
      "NavLinkMatch": 1,
      "Href": "/gateway/plugin",
      "CreateTime": "5/11/2024 04:08:09.92",
      "CreateUser": null,
      "CreateUserId": 0,
      "IsDelete": "0",
      "UpdateTime": "5/11/2024 04:28:42.827",
      "UpdateUser": null,
      "UpdateUserId": null,
      "SortCode": 0,
      "ExtJson": null
    },
    {
      "Id": 61000012000,
      "ParentId": 6100001,
      "Module": 6,
      "Title": "插件调试",
      "Icon": "fas fa-bug",
      "Code": "System",
      "Category": 1,
      "Target": 0,
      "NavLinkMatch": 1,
      "Href": "/gateway/driverdebug",
      "CreateTime": "5/11/2024 04:08:09.92",
      "CreateUser": null,
      "CreateUserId": 0,
      "IsDelete": "0",
      "UpdateTime": "5/11/2024 04:28:42.827",
      "UpdateUser": null,
      "UpdateUserId": null,
      "SortCode": 0,
      "ExtJson": null
    },
    {
      "Id": 6100003,
      "ParentId": 0,
      "Module": 6,
      "Title": "网关日志",
      "Icon": "fas fa-journal-whills",
      "Code": "System",
      "Category": 1,
      "Target": 0,
      "NavLinkMatch": 1,
      "Href": null,
      "CreateTime": "5/11/2024 04:08:09.92",
      "CreateUser": null,
      "CreateUserId": 0,
      "IsDelete": "0",
      "UpdateTime": "5/11/2024 04:28:42.827",
      "UpdateUser": null,
      "UpdateUserId": null,
      "SortCode": 102,
      "ExtJson": null
    },
    {
      "Id": 6100002,
      "ParentId": 0,
      "Module": 6,
      "Title": "网关状态",
      "Icon": "fa-solid fa-users-gear",
      "Code": "System",
      "Category": 1,
      "Target": 0,
      "NavLinkMatch": 1,
      "Href": null,
      "CreateTime": "5/11/2024 04:08:09.92",
      "CreateUser": null,
      "CreateUserId": 0,
      "IsDelete": "0",
      "UpdateTime": "5/11/2024 04:28:42.827",
      "UpdateUser": null,
      "UpdateUserId": null,
      "SortCode": 101,
      "ExtJson": null
    },
    {
      "Id": 6100001,
      "ParentId": 0,
      "Module": 6,
      "Title": "网关管理",
      "Icon": "fa-solid fa-users-gear",
      "Code": "System",
      "Category": 1,
      "Target": 0,
      "NavLinkMatch": 1,
      "Href": null,
      "CreateTime": "5/11/2024 04:08:09.92",
      "CreateUser": null,
      "CreateUserId": 0,
      "IsDelete": "0",
      "UpdateTime": "5/11/2024 04:28:42.827",
      "UpdateUser": null,
      "UpdateUserId": null,
      "SortCode": 100,
      "ExtJson": null
    },
    {
      "Id": 608610055675973,
      "ParentId": 0,
      "Module": 6,
      "Title": "权限管理",
      "Icon": "fa-solid fa-users-gear",
      "Code": "34R8F3KKaz",
      "Category": 1,
      "Target": 0,
      "NavLinkMatch": 1,
      "Href": null,
      "CreateTime": "5/11/2024 04:20:41.397",
      "CreateUser": "SuperAdmin",
      "CreateUserId": 212725263002001,
      "IsDelete": "0",
      "UpdateTime": null,
      "UpdateUser": null,
      "UpdateUserId": null,
      "SortCode": 103,
      "ExtJson": null
    },
    {
      "Id": 608610055680085,
      "ParentId": 608610055680078,
      "Module": 6,
      "Title": "删除",
      "Icon": null,
      "Code": "91320irmQJ",
      "Category": 2,
      "Target": null,
      "NavLinkMatch": null,
      "Href": null,
      "CreateTime": "5/11/2024 04:20:41.4",
      "CreateUser": "SuperAdmin",
      "CreateUserId": 212725263002001,
      "IsDelete": "0",
      "UpdateTime": null,
      "UpdateUser": null,
      "UpdateUserId": null,
      "SortCode": 3,
      "ExtJson": null
    },
    {
      "Id": 608610055680084,
      "ParentId": 608610055680078,
      "Module": 6,
      "Title": "编辑",
      "Icon": null,
      "Code": "F9auu3jy8u",
      "Category": 2,
      "Target": null,
      "NavLinkMatch": null,
      "Href": null,
      "CreateTime": "5/11/2024 04:20:41.4",
      "CreateUser": "SuperAdmin",
      "CreateUserId": 212725263002001,
      "IsDelete": "0",
      "UpdateTime": null,
      "UpdateUser": null,
      "UpdateUserId": null,
      "SortCode": 2,
      "ExtJson": null
    },
    {
      "Id": 608610055680083,
      "ParentId": 608610055680078,
      "Module": 6,
      "Title": "查询",
      "Icon": null,
      "Code": "1HK67pPN3U",
      "Category": 2,
      "Target": null,
      "NavLinkMatch": null,
      "Href": null,
      "CreateTime": "5/11/2024 04:20:41.4",
      "CreateUser": "SuperAdmin",
      "CreateUserId": 212725263002001,
      "IsDelete": "0",
      "UpdateTime": null,
      "UpdateUser": null,
      "UpdateUserId": null,
      "SortCode": 1,
      "ExtJson": null
    },
    {
      "Id": 608610055680082,
      "ParentId": 608610055680078,
      "Module": 6,
      "Title": "新增",
      "Icon": null,
      "Code": "r3wXnioQ8J",
      "Category": 2,
      "Target": null,
      "NavLinkMatch": null,
      "Href": null,
      "CreateTime": "5/11/2024 04:20:41.4",
      "CreateUser": "SuperAdmin",
      "CreateUserId": 212725263002001,
      "IsDelete": "0",
      "UpdateTime": null,
      "UpdateUser": null,
      "UpdateUserId": null,
      "SortCode": 1,
      "ExtJson": null
    },
    {
      "Id": 608610055680081,
      "ParentId": 608610055680078,
      "Module": 6,
      "Title": "授权Api",
      "Icon": null,
      "Code": "Op186zJj26",
      "Category": 2,
      "Target": null,
      "NavLinkMatch": null,
      "Href": null,
      "CreateTime": "5/11/2024 04:20:41.4",
      "CreateUser": "SuperAdmin",
      "CreateUserId": 212725263002001,
      "IsDelete": "0",
      "UpdateTime": null,
      "UpdateUser": null,
      "UpdateUserId": null,
      "SortCode": 0,
      "ExtJson": null
    },
    {
      "Id": 608610055680080,
      "ParentId": 608610055680078,
      "Module": 6,
      "Title": "授权用户",
      "Icon": null,
      "Code": "6Xmk1tH3kb",
      "Category": 2,
      "Target": null,
      "NavLinkMatch": null,
      "Href": null,
      "CreateTime": "5/11/2024 04:20:41.4",
      "CreateUser": "SuperAdmin",
      "CreateUserId": 212725263002001,
      "IsDelete": "0",
      "UpdateTime": null,
      "UpdateUser": null,
      "UpdateUserId": null,
      "SortCode": 0,
      "ExtJson": null
    },
    {
      "Id": 608610055680079,
      "ParentId": 608610055680078,
      "Module": 6,
      "Title": "授权资源",
      "Icon": null,
      "Code": "4jl595cskE",
      "Category": 2,
      "Target": null,
      "NavLinkMatch": null,
      "Href": null,
      "CreateTime": "5/11/2024 04:20:41.4",
      "CreateUser": "SuperAdmin",
      "CreateUserId": 212725263002001,
      "IsDelete": "0",
      "UpdateTime": null,
      "UpdateUser": null,
      "UpdateUserId": null,
      "SortCode": 0,
      "ExtJson": null
    },
    {
      "Id": 608610055680078,
      "ParentId": 608610055675973,
      "Module": 6,
      "Title": "角色管理",
      "Icon": "fa-solid fa-users-gear",
      "Code": "g9ruOH29Yz",
      "Category": 1,
      "Target": 0,
      "NavLinkMatch": 1,
      "Href": "/admin/role",
      "CreateTime": "5/11/2024 04:20:41.4",
      "CreateUser": "SuperAdmin",
      "CreateUserId": 212725263002001,
      "IsDelete": "0",
      "UpdateTime": null,
      "UpdateUser": null,
      "UpdateUserId": null,
      "SortCode": 2,
      "ExtJson": null
    },
    {
      "Id": 608610055680077,
      "ParentId": 608610055680073,
      "Module": 6,
      "Title": "删除",
      "Icon": null,
      "Code": "9E5uA0dugU",
      "Category": 2,
      "Target": null,
      "NavLinkMatch": null,
      "Href": null,
      "CreateTime": "5/11/2024 04:20:41.4",
      "CreateUser": "SuperAdmin",
      "CreateUserId": 212725263002001,
      "IsDelete": "0",
      "UpdateTime": null,
      "UpdateUser": null,
      "UpdateUserId": null,
      "SortCode": 3,
      "ExtJson": null
    },
    {
      "Id": 608610055680076,
      "ParentId": 608610055680073,
      "Module": 6,
      "Title": "编辑",
      "Icon": null,
      "Code": "J7XxGW1PrN",
      "Category": 2,
      "Target": null,
      "NavLinkMatch": null,
      "Href": null,
      "CreateTime": "5/11/2024 04:20:41.4",
      "CreateUser": "SuperAdmin",
      "CreateUserId": 212725263002001,
      "IsDelete": "0",
      "UpdateTime": null,
      "UpdateUser": null,
      "UpdateUserId": null,
      "SortCode": 2,
      "ExtJson": null
    },
    {
      "Id": 608610055680075,
      "ParentId": 608610055680073,
      "Module": 6,
      "Title": "新增",
      "Icon": null,
      "Code": "1us8wr445n",
      "Category": 2,
      "Target": null,
      "NavLinkMatch": null,
      "Href": null,
      "CreateTime": "5/11/2024 04:20:41.4",
      "CreateUser": "SuperAdmin",
      "CreateUserId": 212725263002001,
      "IsDelete": "0",
      "UpdateTime": null,
      "UpdateUser": null,
      "UpdateUserId": null,
      "SortCode": 1,
      "ExtJson": null
    },
    {
      "Id": 608610055680074,
      "ParentId": 608610055680073,
      "Module": 6,
      "Title": "查询",
      "Icon": null,
      "Code": "Kp0A7X4j38",
      "Category": 2,
      "Target": null,
      "NavLinkMatch": null,
      "Href": null,
      "CreateTime": "5/11/2024 04:20:41.4",
      "CreateUser": "SuperAdmin",
      "CreateUserId": 212725263002001,
      "IsDelete": "0",
      "UpdateTime": null,
      "UpdateUser": null,
      "UpdateUserId": null,
      "SortCode": 1,
      "ExtJson": null
    },
    {
      "Id": 608610055680073,
      "ParentId": 608610055675973,
      "Module": 6,
      "Title": "机构管理",
      "Icon": "fa-solid fa-user-gear",
      "Code": "qCvpBAAi96",
      "Category": 1,
      "Target": 0,
      "NavLinkMatch": 1,
      "Href": "/admin/org",
      "CreateTime": "5/11/2024 04:20:41.4",
      "CreateUser": "SuperAdmin",
      "CreateUserId": 212725263002001,
      "IsDelete": "0",
      "UpdateTime": null,
      "UpdateUser": null,
      "UpdateUserId": null,
      "SortCode": 1,
      "ExtJson": null
    },
    {
      "Id": 608610055680072,
      "ParentId": 608610055675983,
      "Module": 6,
      "Title": "删除",
      "Icon": null,
      "Code": "D17eKxr03Z",
      "Category": 2,
      "Target": null,
      "NavLinkMatch": null,
      "Href": null,
      "CreateTime": "5/11/2024 04:20:41.4",
      "CreateUser": "SuperAdmin",
      "CreateUserId": 212725263002001,
      "IsDelete": "0",
      "UpdateTime": null,
      "UpdateUser": null,
      "UpdateUserId": null,
      "SortCode": 3,
      "ExtJson": null
    },
    {
      "Id": 608610055680071,
      "ParentId": 608610055675983,
      "Module": 6,
      "Title": "编辑",
      "Icon": null,
      "Code": "BcWV3Xe7Fs",
      "Category": 2,
      "Target": null,
      "NavLinkMatch": null,
      "Href": null,
      "CreateTime": "5/11/2024 04:20:41.4",
      "CreateUser": "SuperAdmin",
      "CreateUserId": 212725263002001,
      "IsDelete": "0",
      "UpdateTime": null,
      "UpdateUser": null,
      "UpdateUserId": null,
      "SortCode": 2,
      "ExtJson": null
    },
    {
      "Id": 608610055680070,
      "ParentId": 608610055675983,
      "Module": 6,
      "Title": "新增",
      "Icon": null,
      "Code": "X6ySOA55Uu",
      "Category": 2,
      "Target": null,
      "NavLinkMatch": null,
      "Href": null,
      "CreateTime": "5/11/2024 04:20:41.4",
      "CreateUser": "SuperAdmin",
      "CreateUserId": 212725263002001,
      "IsDelete": "0",
      "UpdateTime": null,
      "UpdateUser": null,
      "UpdateUserId": null,
      "SortCode": 1,
      "ExtJson": null
    },
    {
      "Id": 608610055680069,
      "ParentId": 608610055675983,
      "Module": 6,
      "Title": "查询",
      "Icon": null,
      "Code": "m5rhU5eVlj",
      "Category": 2,
      "Target": null,
      "NavLinkMatch": null,
      "Href": null,
      "CreateTime": "5/11/2024 04:20:41.4",
      "CreateUser": "SuperAdmin",
      "CreateUserId": 212725263002001,
      "IsDelete": "0",
      "UpdateTime": null,
      "UpdateUser": null,
      "UpdateUserId": null,
      "SortCode": 1,
      "ExtJson": null
    },
    {
      "Id": 608610055675983,
      "ParentId": 608610055675973,
      "Module": 6,
      "Title": "职位管理",
      "Icon": "fa-solid fa-user-gear",
      "Code": "WycbQ03v3v",
      "Category": 1,
      "Target": 0,
      "NavLinkMatch": 1,
      "Href": "/admin/position",
      "CreateTime": "5/11/2024 04:20:41.4",
      "CreateUser": "SuperAdmin",
      "CreateUserId": 212725263002001,
      "IsDelete": "0",
      "UpdateTime": null,
      "UpdateUser": null,
      "UpdateUserId": null,
      "SortCode": 1,
      "ExtJson": null
    },
    {
      "Id": 608610055675982,
      "ParentId": 608610055675974,
      "Module": 6,
      "Title": "删除",
      "Icon": null,
      "Code": "7eacu1j6a0",
      "Category": 2,
      "Target": null,
      "NavLinkMatch": null,
      "Href": null,
      "CreateTime": "5/11/2024 04:20:41.4",
      "CreateUser": "SuperAdmin",
      "CreateUserId": 212725263002001,
      "IsDelete": "0",
      "UpdateTime": null,
      "UpdateUser": null,
      "UpdateUserId": null,
      "SortCode": 3,
      "ExtJson": null
    },
    {
      "Id": 608610055675981,
      "ParentId": 608610055675974,
      "Module": 6,
      "Title": "编辑",
      "Icon": null,
      "Code": "I9Qx4UIk0i",
      "Category": 2,
      "Target": null,
      "NavLinkMatch": null,
      "Href": null,
      "CreateTime": "5/11/2024 04:20:41.4",
      "CreateUser": "SuperAdmin",
      "CreateUserId": 212725263002001,
      "IsDelete": "0",
      "UpdateTime": null,
      "UpdateUser": null,
      "UpdateUserId": null,
      "SortCode": 2,
      "ExtJson": null
    },
    {
      "Id": 608610055675980,
      "ParentId": 608610055675974,
      "Module": 6,
      "Title": "新增",
      "Icon": null,
      "Code": "hd8Du4w17Z",
      "Category": 2,
      "Target": null,
      "NavLinkMatch": null,
      "Href": null,
      "CreateTime": "5/11/2024 04:20:41.4",
      "CreateUser": "SuperAdmin",
      "CreateUserId": 212725263002001,
      "IsDelete": "0",
      "UpdateTime": null,
      "UpdateUser": null,
      "UpdateUserId": null,
      "SortCode": 1,
      "ExtJson": null
    },
    {
      "Id": 608610055675979,
      "ParentId": 608610055675974,
      "Module": 6,
      "Title": "查询",
      "Icon": null,
      "Code": "POdzOb4P9T",
      "Category": 2,
      "Target": null,
      "NavLinkMatch": null,
      "Href": null,
      "CreateTime": "5/11/2024 04:20:41.4",
      "CreateUser": "SuperAdmin",
      "CreateUserId": 212725263002001,
      "IsDelete": "0",
      "UpdateTime": null,
      "UpdateUser": null,
      "UpdateUserId": null,
      "SortCode": 1,
      "ExtJson": null
    },
    {
      "Id": 608610055675978,
      "ParentId": 608610055675974,
      "Module": 6,
      "Title": "授权Api",
      "Icon": null,
      "Code": "IsM9zLgDNw",
      "Category": 2,
      "Target": null,
      "NavLinkMatch": null,
      "Href": null,
      "CreateTime": "5/11/2024 04:20:41.4",
      "CreateUser": "SuperAdmin",
      "CreateUserId": 212725263002001,
      "IsDelete": "0",
      "UpdateTime": null,
      "UpdateUser": null,
      "UpdateUserId": null,
      "SortCode": 0,
      "ExtJson": null
    },
    {
      "Id": 608610055675977,
      "ParentId": 608610055675974,
      "Module": 6,
      "Title": "授权资源",
      "Icon": null,
      "Code": "MHmOx74s3Y",
      "Category": 2,
      "Target": null,
      "NavLinkMatch": null,
      "Href": null,
      "CreateTime": "5/11/2024 04:20:41.4",
      "CreateUser": "SuperAdmin",
      "CreateUserId": 212725263002001,
      "IsDelete": "0",
      "UpdateTime": null,
      "UpdateUser": null,
      "UpdateUserId": null,
      "SortCode": 0,
      "ExtJson": null
    },
    {
      "Id": 608610055675976,
      "ParentId": 608610055675974,
      "Module": 6,
      "Title": "授权角色",
      "Icon": null,
      "Code": "38yg1d1YH8",
      "Category": 2,
      "Target": null,
      "NavLinkMatch": null,
      "Href": null,
      "CreateTime": "5/11/2024 04:20:41.4",
      "CreateUser": "SuperAdmin",
      "CreateUserId": 212725263002001,
      "IsDelete": "0",
      "UpdateTime": null,
      "UpdateUser": null,
      "UpdateUserId": null,
      "SortCode": 0,
      "ExtJson": null
    },
    {
      "Id": 608610055675975,
      "ParentId": 608610055675974,
      "Module": 6,
      "Title": "重置密码",
      "Icon": null,
      "Code": "0z3V00in43",
      "Category": 2,
      "Target": null,
      "NavLinkMatch": null,
      "Href": null,
      "CreateTime": "5/11/2024 04:20:41.4",
      "CreateUser": "SuperAdmin",
      "CreateUserId": 212725263002001,
      "IsDelete": "0",
      "UpdateTime": null,
      "UpdateUser": null,
      "UpdateUserId": null,
      "SortCode": 0,
      "ExtJson": null
    },
    {
      "Id": 608610055675974,
      "ParentId": 608610055675973,
      "Module": 6,
      "Title": "用户管理",
      "Icon": "fa-solid fa-user-gear",
      "Code": "pQLNfSYZ0v",
      "Category": 1,
      "Target": 0,
      "NavLinkMatch": 1,
      "Href": "/admin/user",
      "CreateTime": "5/11/2024 04:20:41.4",
      "CreateUser": "SuperAdmin",
      "CreateUserId": 212725263002001,
      "IsDelete": "0",
      "UpdateTime": null,
      "UpdateUser": null,
      "UpdateUserId": null,
      "SortCode": 1,
      "ExtJson": null
    }
  ]
}
